darca_storage/__init__.py
darca_storage/__version__.py
darca_storage/backends/local_file_backend.py
darca_storage/client.py
darca_storage/connectors/local.py
darca_storage/decorators/scoped_backend.py
darca_storage/exceptions.py
darca_storage/factory.py
darca_storage/interfaces/credential_aware.py
darca_storage/interfaces/file_backend.py
darca_storage/interfaces/storage_connector.py
darca_storage-0.0.1.dist-info/LICENSE
darca_storage-0.0.1.dist-info/METADATA
darca_storage-0.0.1.dist-info/WHEEL
darca_storage-0.0.1.dist-info/RECORD
