Metadata-Version: 2.3
Name: darca-storage
Version: 0.0.1
Summary: Storage instance with file operation support for multiple backends.
License: LICENSE
Author: Roel Kist
Author-email: roel.kist@gmail.com
Requires-Python: >=3.12,<4.0
Classifier: License :: Other/Proprietary License
Classifier: Programming Language :: Python :: 3
Classifier: Programming Language :: Python :: 3.12
Classifier: Programming Language :: Python :: 3.13
Requires-Dist: darca-exception (>=0.1.1,<0.2.0)
Requires-Dist: darca-file-utils (>=0.1.1,<0.2.0)
Requires-Dist: darca-log-facility (>=0.1.0,<0.2.0)
Requires-Dist: typing-extensions (>=4.13.2,<5.0.0)
